ttt.v
module tic_tac_toe (
    input clk,
    input reset,
    input [3:0] cell_select,
    input place,

    output reg current_player,
    output reg game_over,
    output reg [1:0] winner
);

    reg [1:0] board [0:8];
    integer i;

    always @(posedge clk or posedge reset) begin
        if (reset) begin
            for (i = 0; i < 9; i = i + 1)
                board[i] <= 2'b00;

            current_player <= 1'b0;
            game_over <= 1'b0;
            winner <= 2'b00;
        end
        else if (place && !game_over) begin
            if (board[cell_select] == 2'b00) begin
                board[cell_select] <= current_player ? 2'b10 : 2'b01;
                current_player <= ~current_player;
            end
        end
    end

    always @(*) begin
        winner = 2'b00;
        game_over = 1'b0;

        if (board[0] != 0 && board[0] == board[1] && board[1] == board[2])
            winner = board[0];
        else if (board[3] != 0 && board[3] == board[4] && board[4] == board[5])
            winner = board[3];
        else if (board[6] != 0 && board[6] == board[7] && board[7] == board[8])
            winner = board[6];

        else if (board[0] != 0 && board[0] == board[3] && board[3] == board[6])
            winner = board[0];
        else if (board[1] != 0 && board[1] == board[4] && board[4] == board[7])
            winner = board[1];
        else if (board[2] != 0 && board[2] == board[5] && board[5] == board[8])
            winner = board[2];

        else if (board[0] != 0 && board[0] == board[4] && board[4] == board[8])
            winner = board[0];
        else if (board[2] != 0 && board[2] == board[4] && board[4] == board[6])
            winner = board[2];

        if (winner != 2'b00)
            game_over = 1'b1;
    end
endmodule

3t_tb.v
`timescale 1ns/1ps
`include "ttt.v"

module tb_tic_tac_toe;

    reg clk;
    reg reset;
    reg [3:0] cell_select;
    reg place;

    wire current_player;
    wire game_over;
    wire [1:0] winner;

    // Instantiate the DUT (Device Under Test)
    tic_tac_toe uut (
        .clk(clk),
        .reset(reset),
        .cell_select(cell_select),
        .place(place),
        .current_player(current_player),
        .game_over(game_over),
        .winner(winner)
    );
    initial begin
        $dumpfile("3t_tb.vcd");
        $dumpvars(0,tb_tic_tac_toe);
        
    end

    // Clock generation: 10 ns period
    always #5 clk = ~clk;

    initial begin
        // Initialize signals
        clk = 0;
        reset = 1;
        place = 0;
        cell_select = 0;

        // Apply reset
        #10;
        reset = 0;

        // -------- Game sequence --------
        // Player X -> cell 0
        #10 cell_select = 0; place = 1;
        #10 place = 0;

        // Player O -> cell 3
        #10 cell_select = 3; place = 1;
        #10 place = 0;

        // Player X -> cell 1
        #10 cell_select = 1; place = 1;
        #10 place = 0;

        // Player O -> cell 4
        #10 cell_select = 4; place = 1;
        #10 place = 0;

        // Player X -> cell 2 (X wins)
        #10 cell_select = 2; place = 1;
        #10 place = 0;

        // Wait and observe result
        #20;

        // End simulation
        $stop;
    end

endmodule

3t_tb.vcd
$date
	Thu Feb 05 15:02:37 2026
$end
$version
	Icarus Verilog
$end
$timescale
	1ps
$end
$scope module tb_tic_tac_toe $end
$var wire 2 ! winner [1:0] $end
$var wire 1 " game_over $end
$var wire 1 # current_player $end
$var reg 4 $ cell_select [3:0] $end
$var reg 1 % clk $end
$var reg 1 & place $end
$var reg 1 ' reset $end
$scope module uut $end
$var wire 4 ( cell_select [3:0] $end
$var wire 1 % clk $end
$var wire 1 & place $end
$var wire 1 ' reset $end
$var reg 1 # current_player $end
$var reg 1 " game_over $end
$var reg 2 ) winner [1:0] $end
$var integer 32 * i [31:0] $end
$upscope $end
$upscope $end
$enddefinitions $end
$comment Show the parameter values. $end
$dumpall
$end
#0
$dumpvars
b1001 *
b0 )
b0 (
1'
0&
0%
b0 $
0#
0"
b0 !
$end
#5000
b1001 *
1%
#10000
0%
0'
#15000
1%
#20000
0%
1&
#25000
1#
1%
#30000
0%
0&
#35000
1%
#40000
0%
1&
b11 $
b11 (
#45000
0#
1%
#50000
0%
0&
#55000
1%
#60000
0%
1&
b1 $
b1 (
#65000
1#
1%
#70000
0%
0&
#75000
1%
#80000
0%
1&
b100 $
b100 (
#85000
0#
1%
#90000
0%
0&
#95000
1%
#100000
0%
1&
b10 $
b10 (
#105000
1"
b1 !
b1 )
1#
1%
#110000
0%
0&
